{
  "$schema" : "https:\/\/schema.linearmouse.app\/0.10.2",
  "schemes" : [
    {
      "if" : {
        "device" : {
          "category" : "mouse",
          "productID" : "0xb037",
          "productName" : "MX Anywhere 3S",
          "serialNumber" : "95625B2D",
          "vendorID" : "0x46d"
        }
      },
      "pointer" : {
        "acceleration" : 0.6921
      },
      "scrolling" : {
        "acceleration" : {
          "vertical" : 0.6
        },
        "distance" : {
          "vertical" : "auto"
        },
        "modifiers" : {
          "vertical" : {
            "command" : {
              "type" : "pinchZoom"
            }
          }
        },
        "reverse" : {
          "vertical" : false
        },
        "speed" : {
          "vertical" : 40.41
        }
      }
    },
    {
      "if" : {
        "device" : {
          "category" : "trackpad",
          "productID" : "0x0",
          "productName" : "Apple Internal Keyboard \/ Trackpad",
          "vendorID" : "0x0"
        }
      },
      "scrolling" : {
        "reverse" : {
          "vertical" : false
        }
      }
    }
  ]
}